.coveragerc
.gitignore
.travis.yml
LICENSE
README.md
conftest.py
setup.py
tox.ini
meta/__init__.py
meta.data.egg-info/PKG-INFO
meta.data.egg-info/SOURCES.txt
meta.data.egg-info/dependency_links.txt
meta.data.egg-info/entry_points.txt
meta.data.egg-info/namespace_packages.txt
meta.data.egg-info/requires.txt
meta.data.egg-info/top_level.txt
meta/data/__init__.py
meta/data/pg.py
meta/data/resource.py
meta/data/settings.py
meta/data/migrations/0001-add-meta-table/backward.sql
meta/data/migrations/0001-add-meta-table/forward.sql
tests/test_db.py
tests/test_meta.py