Metadata-Version: 1.0
Name: meta.data
Version: 0.1
Summary: Stores data about data
Home-page: https://github.com/dmonroy/meta.data
Author: Darwin Monroy
Author-email: contact@darwinmonroy.com
License: MIT License
Platform: UNKNOWN
